OCP.cp39-win_amd64.pyd
ocp_vtk-7.5.3.0.data/platlib/.load-order-ocp_vtk-7.5.3.0
ocp_vtk-7.5.3.0.data/platlib/charset-f1ff420e.dll
ocp_vtk-7.5.3.0.data/platlib/freetype-4118af61.dll
ocp_vtk-7.5.3.0.data/platlib/gl2ps-d5be8415.dll
ocp_vtk-7.5.3.0.data/platlib/glew32-45501540.dll
ocp_vtk-7.5.3.0.data/platlib/hdf-839eff43.dll
ocp_vtk-7.5.3.0.data/platlib/hdf5-4fe83a80.dll
ocp_vtk-7.5.3.0.data/platlib/hdf5_hl-1e917a47.dll
ocp_vtk-7.5.3.0.data/platlib/iconv-cfade252.dll
ocp_vtk-7.5.3.0.data/platlib/jbig-283e2ee0.dll
ocp_vtk-7.5.3.0.data/platlib/jsoncpp-74e0510f.dll
ocp_vtk-7.5.3.0.data/platlib/Lerc-d98a2f21.dll
ocp_vtk-7.5.3.0.data/platlib/libbz2-bf72f086.dll
ocp_vtk-7.5.3.0.data/platlib/libcrypto-3-x64-79e66d5d.dll
ocp_vtk-7.5.3.0.data/platlib/libcurl-4715d16f.dll
ocp_vtk-7.5.3.0.data/platlib/libdeflate-b8e589f8.dll
ocp_vtk-7.5.3.0.data/platlib/libexpat-f770ecdf.dll
ocp_vtk-7.5.3.0.data/platlib/liblz4-b9e0f074.dll
ocp_vtk-7.5.3.0.data/platlib/liblzma-f8552861.dll
ocp_vtk-7.5.3.0.data/platlib/libpng16-f2a3ac70.dll
ocp_vtk-7.5.3.0.data/platlib/libssh2-54993272.dll
ocp_vtk-7.5.3.0.data/platlib/libxml2-64eb6d5f.dll
ocp_vtk-7.5.3.0.data/platlib/mfhdf-b1f9baf5.dll
ocp_vtk-7.5.3.0.data/platlib/msvcp140.dll
ocp_vtk-7.5.3.0.data/platlib/netcdf-b8bee6dc.dll
ocp_vtk-7.5.3.0.data/platlib/ogg-e38dc37e.dll
ocp_vtk-7.5.3.0.data/platlib/proj_7_2-671605b1.dll
ocp_vtk-7.5.3.0.data/platlib/sqlite3-dd39700b.dll
ocp_vtk-7.5.3.0.data/platlib/tbb-17b02d2c.dll
ocp_vtk-7.5.3.0.data/platlib/tbbmalloc-24341326.dll
ocp_vtk-7.5.3.0.data/platlib/theora-ad1efaaf.dll
ocp_vtk-7.5.3.0.data/platlib/tiff-9eb9c421.dll
ocp_vtk-7.5.3.0.data/platlib/TKernel-d4900e62.dll
ocp_vtk-7.5.3.0.data/platlib/TKG2d-af7ff42f.dll
ocp_vtk-7.5.3.0.data/platlib/TKG3d-2f65fb9e.dll
ocp_vtk-7.5.3.0.data/platlib/TKMath-e14c04cc.dll
ocp_vtk-7.5.3.0.data/platlib/vtkChartsCore-9.0-a07ade5b.dll
ocp_vtk-7.5.3.0.data/platlib/vtkCommonColor-9.0-87ee4902.dll
ocp_vtk-7.5.3.0.dist-info/DELVEWHEEL
ocp_vtk-7.5.3.0.dist-info/LICENSE
ocp_vtk-7.5.3.0.dist-info/LICENSES_bundled
ocp_vtk-7.5.3.0.dist-info/METADATA
ocp_vtk-7.5.3.0.dist-info/RECORD
ocp_vtk-7.5.3.0.dist-info/top_level.txt
ocp_vtk-7.5.3.0.dist-info/WHEEL
