Metadata-Version: 2.1
Name: ocp-vtk
Version: 7.5.3.0
Summary: OCP+VTK wheel with shared library dependencies bundled.
Home-page: https://github.com/roipoussiere/OCP
Download-URL: https://github.com/roipoussiere/OCP/releases
Author: fp473, roipoussiere
License: UNKNOWN
Platform: UNKNOWN
Classifier: Development Status :: 4 - Beta
Classifier: Intended Audience :: Developers
Classifier: Intended Audience :: Science/Research
Classifier: License :: OSI Approved :: Apache Software License
Classifier: Operating System :: POSIX
Classifier: Operating System :: MacOS
Classifier: Operating System :: Unix
Classifier: Programming Language :: Python
Classifier: Topic :: Software Development :: Libraries :: Python Modules
Classifier: Topic :: Scientific/Engineering
License-File: LICENSE
License-File: LICENSES_bundled
